rewordapp/__init__.py
rewordapp/__main__.py
rewordapp/application.py
rewordapp/config.py
rewordapp/main.py
rewordapp-0.0.4.dist-info/LICENSE
rewordapp-0.0.4.dist-info/METADATA
rewordapp-0.0.4.dist-info/WHEEL
rewordapp-0.0.4.dist-info/entry_points.txt
rewordapp-0.0.4.dist-info/top_level.txt
rewordapp-0.0.4.dist-info/RECORD
