Metadata-Version: 2.1
Name: rewordapp
Version: 0.0.4
Summary: The application to reword text.
Home-page: https://github.com/Geeks-Trident-LLC/rewordapp
Author: Tuyen Mathew Duong
Author-email: tuyen@geekstrident.com
Maintainer: Tuyen Mathew Duong
Maintainer-email: tuyen@geekstrident.com
License: BSD-3-Clause
Platform: UNKNOWN
Classifier: Intended Audience :: Developers
Classifier: Operating System :: MacOS :: MacOS X
Classifier: Operating System :: POSIX :: Linux
Classifier: Operating System :: Microsoft :: Windows
Classifier: License :: OSI Approved :: BSD License
Classifier: Programming Language :: Python
Classifier: Programming Language :: Python :: 3
Classifier: Programming Language :: Python :: 3.5
Classifier: Programming Language :: Python :: 3.6
Classifier: Programming Language :: Python :: 3.7
Classifier: Programming Language :: Python :: 3.8
Classifier: Programming Language :: Python :: 3.9
Classifier: Topic :: Software Development :: Libraries :: Python Modules
